MANIFEST.in
README.md
requirements.txt
revolut_cli.py
revolut_transactions.py
revolutbot.py
setup.cfg
setup.py
revolut/__init__.py
revolut.egg-info/PKG-INFO
revolut.egg-info/SOURCES.txt
revolut.egg-info/dependency_links.txt
revolut.egg-info/requires.txt
revolut.egg-info/top_level.txt
revolut_bot/__init__.py
test/test_revolut.py
test/test_revolut_bot.py