Metadata-Version: 1.2
Name: revolut
Version: 0.1.2
Summary: Package to get account balances and do operations on Revolut
Home-page: https://github.com/tducret/revolut-python
Author: Thibault Ducret
Author-email: thibault.ducret@gmail.com
License: MIT
Download-URL: https://github.com/tducret/revolut-python/tarball/0.1.2
Keywords: api,revolut,bank,parsing,cli,python-wrapper,scraping,scraper,parser
Platform: Posix; MacOS X
Classifier: Programming Language :: Python :: 3
Requires-Python: >=3
